matpylib/__init__.py
matpylib/core.py
matpylib-0.1.3.dist-info/METADATA
matpylib-0.1.3.dist-info/WHEEL
matpylib-0.1.3.dist-info/entry_points.txt
matpylib-0.1.3.dist-info/top_level.txt
matpylib-0.1.3.dist-info/RECORD
